{
	"events": [
		{
			"title": "What is SoDA and can I drink it?",
			"sponsor": "",
			"showEndTime": false,
			"start": {
				"year": 2021,
				"month": 7,
				"day": 31,
				"hour": 19,
				"minute": 0
			},
			"end": {
				"year": 2021,
				"month": 7,
				"day": 31,
				"hour": 21,
				"minute": 0
			},
			"description": "Kick off the beginning of the year with a welcome back from SoDA! Join us for our info session, we will be going over what you can look forward to in SoDA this semester!",
			"location": "CAVC 351",
			"RSVP_link": "https://docs.google.com/forms/d/e/1FAIpQLSedNgM8U_MNclP3gJUklXdJOd1xPEyHsDBEd_G3EtHgsCKnUQ/viewform"
		},
		{
			"title": "Resume Reviews",
			"sponsor": "",
			"showEndTime": false,
			"start": {
				"year": 2021,
				"month": 8,
				"day": 7,
				"hour": 19,
				"minute": 0
			},
			"end": {
				"year": 2021,
				"month": 8,
				"day": 7,
				"hour": 21,
				"minute": 0
			},
			"description": "Bring your resume to SoDA to learn the best tips and tricks on making a great resume! Don’t have one? Come learn about the fundamentals and build one from the ground up!",
			"location": "CAVC 351",
			"RSVP_link": "https://docs.google.com/forms/d/e/1FAIpQLSeW1kswuZePy-wMSnJZN7ZsMqwNhU34FnVFglEmIWkDux7YTA/viewform"
		},
		{
			"title": "A Day in the Life with Walmart",
			"sponsor": "",
			"showEndTime": false,
			"start": {
				"year": 2021,
				"month": 8,
				"day": 14,
				"hour": 19,
				"minute": 0
			},
			"end": {
				"year": 2021,
				"month": 8,
				"day": 14,
				"hour": 21,
				"minute": 0
			},
			"description": "Learn about opportunities at Walmart and what it is like to work there!",
			"location": "CAVC 351",
			"RSVP_link": "https://docs.google.com/forms/d/e/1FAIpQLSd7a7SuaV3t1Zj6rw2VXhbQ8YmDCzJJEuYRGYvbCAgb6EJiMw/viewform"
		},
		{
			"title": "Technical Interview Prep",
			"sponsor": "",
			"showEndTime": false,
			"start": {
				"year": 2021,
				"month": 8,
				"day": 21,
				"hour": 19,
				"minute": 0
			},
			"end": {
				"year": 2021,
				"month": 8,
				"day": 21,
				"hour": 21,
				"minute": 0
			},
			"description": "Learn all about technical interviews at this week's meeting where we will go over the basics and how you can ace them!",
			"location": "CAVC 351",
			"RSVP_link": "https://docs.google.com/forms/d/e/1FAIpQLSfrL4D-L5r88P8efyR0Fe0aYqLjbm5iok7BHmuNEB289IHgtA/viewform"
		},
		{
			"title": "Behavioral Interview Workshop",
			"sponsor": "",
			"showEndTime": false,
			"start": {
				"year": 2021,
				"month": 8,
				"day": 28,
				"hour": 19,
				"minute": 0
			},
			"end": {
				"year": 2021,
				"month": 8,
				"day": 28,
				"hour": 21,
				"minute": 0
			},
			"description": "Learn about behavioral interviews at this week’s meeting where we will go over how to approach interview questions and practice answering them too!",
			"location": "CAVC Third Floor Atrium",
			"RSVP_link": "https://docs.google.com/forms/d/e/1FAIpQLScrejpiPM-FPfjaJWEE91mLPTZpV-pAGDT-lOL1AQOQzQ-gKA/viewform"
		},
		{
			"title": "Amazon Networking and Information Session",
			"sponsor": "",
			"showEndTime": false,
			"start": {
				"year": 2021,
				"month": 9,
				"day": 5,
				"hour": 19,
				"minute": 0
			},
			"end": {
				"year": 2021,
				"month": 9,
				"day": 5,
				"hour": 21,
				"minute": 0
			},
			"description": "Join us in this week’s event to learn about opportunities at Amazon and network with their representatives!",
			"location": "CAVC Third Floor Atrium",
			"RSVP_link": "https://docs.google.com/forms/d/e/1FAIpQLScltB7ulbb8YzYRJYMKZvCbfKY75UaDzWQeRAAm_E6Q7-jOdg/viewform"
		},
		{
			"title": "Card Games Social",
			"sponsor": "",
			"showEndTime": false,
			"start": {
				"year": 2021,
				"month": 9,
				"day": 26,
				"hour": 19,
				"minute": 0
			},
			"end": {
				"year": 2021,
				"month": 9,
				"day": 26,
				"hour": 21,
				"minute": 0
			},
			"description": "Come by and spend some time at the SoDA social playing some card games! Enjoy food and hang out with SoDA Officers and Members!",
			"location": "CAVC 351",
			"RSVP_link": "https://docs.google.com/forms/d/e/1FAIpQLSf5DmmiIlHNOjg35nWldkniKKUEgcgNzKwJGnypEqPAHcGtwQ/viewform"
		},
		{
			"title": "Git Basics",
			"sponsor": "",
			"showEndTime": false,
			"start": {
				"year": 2021,
				"month": 10,
				"day": 16,
				"hour": 19,
				"minute": 0
			},
			"end": {
				"year": 2021,
				"month": 10,
				"day": 16,
				"hour": 21,
				"minute": 0
			},
			"description": "Come by this week’s meeting to learn about one of the most essential tools in software engineering! We’ll be going over the basics you need to help yourself stand out!",
			"location": "CAVC 351",
			"RSVP_link": "https://docs.google.com/forms/d/e/1FAIpQLSffL6QHUzeO3Hgx2volzFg9IzQqYnU2C0pPOa-UEfQexzlDUg/viewform"
		}
	]
}